LICENSE
MANIFEST.in
README.rst
setup.py
obliquity/__init__.py
obliquity/distributions.py
obliquity/kappa_inference.py
obliquity/sini_inference_fns.c
obliquity/sini_inference_fns.pyx
obliquity.egg-info/PKG-INFO
obliquity.egg-info/SOURCES.txt
obliquity.egg-info/dependency_links.txt
obliquity.egg-info/not-zip-safe
obliquity.egg-info/requires.txt
obliquity.egg-info/top_level.txt
obliquity/data/cosi_pdf_grid.h5
scripts/calc_kappa_posterior
scripts/write_cosi_dist