Metadata-Version: 1.1
Name: obliquity
Version: 0.2
Summary: Infer the stellar obliquity distribution of transiting planet systems.
Home-page: https://github.com/timothydmorton/obliquity
Author: Timothy D. Morton
Author-email: tim.morton@gmail.com
License: UNKNOWN
Platform: UNKNOWN
Classifier: Development Status :: 3 - Alpha
Classifier: Intended Audience :: Science/Research
Classifier: Operating System :: OS Independent
Classifier: Programming Language :: Python
Classifier: Topic :: Scientific/Engineering
Classifier: Topic :: Scientific/Engineering :: Astronomy
